{"name":"ssh","postlist":[{"title":"Routing internet via SSH tunnel on Raspberry Pi","slug":null,"date":"2015-07-24T23:38:00.000Z","updated":"2019-07-03T22:51:02.813Z","comments":null,"path":"api/articles/routing-internet-via-ssh-tunnel-on-raspberry-pi.json","excerpt":null,"keywords":null,"cover":null,"content":null,"raw":null,"categories":null,"tags":[{"name":"linux","path":"api/tags/linux.json"},{"name":"ssh","path":"api/tags/ssh.json"},{"name":"raspberry-pi","path":"api/tags/raspberry-pi.json"}]}]}